{
  "text": "Drone safety Language selection WxT Language switcher Français fr / Gouvernement du Canada Search this site Customize your search tc.canada.ca canada.ca Search Menu Main Menu Home Jobs and the workplace Immigration and citizenship Travel and tourism Business and industry Health Benefits Health – More Taxes Environment and natural resources National security and defence Culture, history and sport Policing, justice and emergencies Transport and infrastructure Canada and the world Money and finances Science and innovation You are here Canada.ca Transport Canada Aviation Drone safety Flying your drone safely and legally, drone registration, drone pilot certification, where and where not to fly, reporting a drone incident. Most requested 2025 Summary of changes to Canada’s drone regulations Transport Canada Aeronautical Information Manual - see Remotely Piloted Aircraft (RPA) Canadian Aviation Regulations - Part IX Get permission for special drone operations Foreign operators in Canada Drone Zone newsletter Services and information Services and information Learn the rules before you fly your drone Rules and regulations, where to fly, choosing a drone, best practices. Drone pilot licensing Getting a drone pilot certificate, find a flight school, get permission for special operations. Registering your drone How to register, benefits, penalties, managing your registration. Drone Management Portal Access your account to register your drone, take an exam, or apply for your pilot certificate. Submitting a drone Safety Assurance Declaration Declare a drone as safe for Advanced or Level 1 Complex operations Drone innovation and collaboration Canadian Drone Advisory Committee, drones in the Canadian Arctic, test ranges, partnerships and collaborations. Help for drone safety partners and manufacturers Safety education and promotional materials. Report a drone incident Complete a drone incident report form. Advanced air mobility Urban Air Mobility (UAM), Regional Air Mobility (RAM), electric vertical takeoff and landing (eVTOL). Contributors From: Transport Canada National Research Council Canada Parks Canada Date modified: 2025-05-09",
  "meta": {
    "title": "Drone safety",
    "source_organization": "Transport Canada",
    "country": "Canada",
    "publication_year": 2025,
    "document_type": "regulation",
    "url": "https://tc.canada.ca/en/aviation/drone-safety#wb-info",
    "trust_score": 0.9,
    "hash_id": "541ec900336e633658365a61777c83665017351a237012e5675b81435a1e2120"
  }
}