{
  "text": "Learn the rules before you fly your drone Language selection WxT Language switcher Français fr / Gouvernement du Canada Search this site Customize your search tc.canada.ca canada.ca Search Menu Main Menu Home Jobs and the workplace Immigration and citizenship Travel and tourism Business and industry Health Benefits Health – More Taxes Environment and natural resources National security and defence Culture, history and sport Policing, justice and emergencies Transport and infrastructure Canada and the world Money and finances Science and innovation You are here Canada.ca Transport Canada Aviation Drone safety Learn the rules before you fly your drone Rules and regulations, where to fly, best practices, help for retailers. Most requested 2025 Summary of changes to Canada’s drone regulations Canadian Aviation Regulations - Part IX Drone Zone newsletter Services and information Services and information Flying your drone safely and legally Rules and regulations, fines and penalties, safety tips. Drone operation categories and pilot certificates Size classification, basic, advanced and complex operations, special flight operations. Where to fly your drone Search the interactive map, sharing airspace safely, prohibited areas. Choosing the right drone Safety assurance ratings and requirements. Get permission for special drone operations Special events, flying beyond visual line-of-sight, foreign operators. Tips and best practices for drone pilots Tips for first time pilots, insurance, understanding urban airflows. Privacy guidelines for drone users Privacy guidelines for recreational, commercial and government drone operators. Contributors From: Transport Canada National Research Council Canada Parks Canada Date modified: 2025-11-04",
  "meta": {
    "title": "Learn the rules before you fly your drone",
    "source_organization": "Transport Canada",
    "country": "Canada",
    "publication_year": 2025,
    "document_type": "regulation",
    "url": "https://tc.canada.ca/en/aviation/drone-safety/learn-rules-you-fly-your-drone",
    "trust_score": 0.9,
    "hash_id": "0c5219df0a1a80e22ca6c1b99275bf44e2937723ff9be16a2a4102de65e52707"
  }
}