{
  "text": "Drone pilot licensing Language selection WxT Language switcher Français fr / Gouvernement du Canada Search this site Customize your search tc.canada.ca canada.ca Search Menu Main Menu Home Jobs and the workplace Immigration and citizenship Travel and tourism Business and industry Health Benefits Health – More Taxes Environment and natural resources National security and defence Culture, history and sport Policing, justice and emergencies Transport and infrastructure Canada and the world Money and finances Science and innovation You are here Canada.ca Transport Canada Aviation Drone safety Drone pilot licensing Getting a drone pilot certificate, find a flight school, permission for special operations, become a flight reviewer. Most requested 2025 Summary of changes to Canada’s drone regulations Drone Management Portal login Self-paced study program Canadian Aviation Regulations - Part IX Standard 921 – Small Remotely Piloted Aircraft in Visual Line-Of-Sight (VLOS) Drone Zone newsletter Services and information Services and information Drone operation categories and pilot certificates Size classification, basic, advanced and complex operations, special flight operations. Get permission for special drone operations Advertised events, foreign operators, medium and high-complexity operations. Find a drone flight school Drone flight training, list of schools. Drone pilot study resources Recommended learning path, study resources. Take a drone pilot exam Eligibility, Small Basic Exam, Advanced Exam, Level 1 Complex Exam Complete a flight review How to schedule a flight review Becoming a flight reviewer for drones Eligibility, getting your flight reviewer rating, recency requirements. Apply for an RPAS Operator Certificate Requirement for Level 1 Complex Operations, how to apply. Keep your drone pilot skills up to date Complete of one of these activities to keep your certificate valid. Contributors From: Transport Canada Date modified: 2025-11-04",
  "meta": {
    "title": "Drone pilot licensing",
    "source_organization": "Transport Canada",
    "country": "Canada",
    "publication_year": 2025,
    "document_type": "regulation",
    "url": "https://tc.canada.ca/en/aviation/drone-safety/drone-pilot-licensing",
    "trust_score": 0.9,
    "hash_id": "e6f0b3685e18bb4a3b336577027f48560313a7747e56d33050d347b6d8e424e4"
  }
}